file_finder/cli.py
file_finder/constants.py
file_finder/exceptions.py
file_finder/finder.py
file_finder/utils.py
phyle_phynder-0.1.1.dist-info/entry_points.txt
phyle_phynder-0.1.1.dist-info/METADATA
phyle_phynder-0.1.1.dist-info/WHEEL
phyle_phynder-0.1.1.dist-info/RECORD
